py3_frida/__init__.py
py3_frida/frida.py
py3_frida-0.0.1.dist-info/METADATA
py3_frida-0.0.1.dist-info/WHEEL
py3_frida-0.0.1.dist-info/licenses/LICENSE
py3_frida-0.0.1.dist-info/RECORD
