Metadata-Version: 2.4
Name: py3-frida
Version: 0.0.1
Summary: 
License-File: LICENSE
Author: mathewgeola
Author-email: mathewgeola@gmail.com
Requires-Python: >=3.12
Classifier: Programming Language :: Python :: 3
Classifier: Programming Language :: Python :: 3.12
Classifier: Programming Language :: Python :: 3.13
Classifier: Programming Language :: Python :: 3.14
Requires-Dist: httpx (>=0.28.1,<0.29.0)
Requires-Dist: parsel (>=1.11.0,<2.0.0)
Requires-Dist: py3-execute (>=0.0.5,<0.0.6)
Requires-Dist: py3-logger (>=0.0.7,<0.0.8)
Requires-Dist: py3-web (>=0.0.7,<0.0.8)
